{
  "type": "FeatureCollection",
  "features": [
    {
      "type": "Feature",
      "geometry": { "type": "Point", "coordinates": [-77.05, 38.87] },
      "properties": { "name": "Mock Pentagon (Overpass API Down)" },
      "id": 1
    }
  ]
}
